{
"FORGOT_EMAIL": "Sie haben Ihre E-Mail-Adresse nicht eingegeben.",
"EMAIL_SHORT": "Ihre E-Mail-Adresse ist zu kurz.",
"EMAIL_LONG": "Ihre E-Mail-Adresse ist zu lang.",
"EMAIL_FORMAT": "Sie haben Ihre E-Mail-Adresse falsch geschrieben.",
"ENTER_PASSWORD": "Sie müssen ein Passwort eingeben.",
"PASS_MIN_LENGTH": "Das Passwort muss mindestens 6 Zeichen lang sein.",
"PASS_NOT_MATCH": "Ihre Passwörter stimmen nicht zusammen.",
"PASS_TWICE": "Sie müssen Ihr Passwort zweimal eingeben.",
"USERNAME_MISSING": "Sie müssen einen Benutzernamen wählen.",
"USERNAME_MIN_LENGTH": "Ihr Benutzername muss mindestens drei Zeichen lang sein.",
"PASSWORD_PROB": "Etwas war falsch mit Ihrem Passwort.",
"USERNAME_PROB": "Etwas war falsch mit Ihrem Benutzername.",
"ACCT_PROB": "Es gab ein Problem mit Ihrem Verzeichnis. Haben Sie sich angemeldet und war Ihren Antrag bearbeitet?",
"HAS_USERNAME": "Es gibt schon ein Verzeichnis mit dieser E-Mail-Adresse. Bitte gehen Sie auf der Login-Seite und stellen das System Ihre Daten zu senden.",
"USERNAME_TAKEN": "Dieser Benutzername ist schon genommen. Bitte wählen Sie eine andere!",
"SUCCESSFUL_UPDATE": "Verzeichnis erfolgreich aktualisiert. Sie können nun in das System einloggen!",
"PROCESSING_ERROR": "Es gibt ein Fehler während der Bearbeitung Ihrer Anfrage. Die Dienstleistungen sind zur Zeit nicht verfügbar."
}